django_object_actions/__init__.py
django_object_actions/models.py
django_object_actions/static/django_object_actions/css/style.css
django_object_actions/templates/django_object_actions/change_form.html
django_object_actions/templates/django_object_actions/change_list.html
django_object_actions/templates/django_object_actions/modal_form.html
django_object_actions/tests/__init__.py
django_object_actions/tests/test_admin.py
django_object_actions/tests/test_urls.py
django_object_actions/tests/test_utils.py
django_object_actions/tests/tests.py
django_object_actions/utils.py
skytek_django_object_actions-5.2.0.dist-info/LICENSE
skytek_django_object_actions-5.2.0.dist-info/METADATA
skytek_django_object_actions-5.2.0.dist-info/WHEEL
skytek_django_object_actions-5.2.0.dist-info/RECORD
