Metadata-Version: 2.1
Name: skytek-django-object-actions
Version: 5.2.0
Summary: A Django app for adding object tools for models in the admin
Home-page: https://github.com/Skytek/django-object-actions
License: Apache-2.0
Keywords: django,admin
Author: crccheck
Author-email: c@crccheck.com
Requires-Python: >=3.7,<4.0
Classifier: Development Status :: 5 - Production/Stable
Classifier: Framework :: Django
Classifier: Intended Audience :: Developers
Classifier: License :: OSI Approved :: Apache Software License
Classifier: Operating System :: OS Independent
Classifier: Programming Language :: Python :: 3
Classifier: Programming Language :: Python :: 3.7
Classifier: Programming Language :: Python :: 3.8
Classifier: Programming Language :: Python :: 3.9
Classifier: Programming Language :: Python :: 3.10
Classifier: Programming Language :: Python :: 3.11
Classifier: Programming Language :: Python :: 3.12
Project-URL: Repository, https://github.com/Skytek/django-object-actions
